healthz/__init__.py
healthz/charts.py
healthz/cli.py
healthz/metrics.py
healthz/monitor.py
healthz/tui.py
healthz-0.1.1.dist-info/METADATA
healthz-0.1.1.dist-info/WHEEL
healthz-0.1.1.dist-info/entry_points.txt
healthz-0.1.1.dist-info/licenses/LICENSE
healthz-0.1.1.dist-info/RECORD
