Metadata-Version: 2.4
Name: healthz
Version: 0.1.1
Summary: Interactive HTTP health monitoring tool with real-time metrics
License: MIT
License-File: LICENSE
Keywords: http,monitoring,health-check,load-testing,performance,async,debugging
Author: Delos Intelligence
Author-email: contact@delos.so
Requires-Python: >=3.10,<4.0
Classifier: Development Status :: 4 - Beta
Classifier: Intended Audience :: Developers
Classifier: License :: OSI Approved :: MIT License
Classifier: Programming Language :: Python :: 3
Classifier: Programming Language :: Python :: 3.10
Classifier: Programming Language :: Python :: 3.11
Classifier: Programming Language :: Python :: 3.12
Classifier: Programming Language :: Python :: 3.13
Classifier: Programming Language :: Python :: 3.14
Classifier: Topic :: System :: Monitoring
Requires-Dist: aiohttp (>=3.9.0,<4.0.0)
Requires-Dist: click (>=8.1.0,<9.0.0)
Requires-Dist: textual (>=0.47.0,<0.48.0)
Requires-Dist: textual-plotext (>=0.2.0,<0.3.0)
Project-URL: Homepage, https://github.com/Delos-Intelligence/healthz
Project-URL: Repository, https://github.com/Delos-Intelligence/healthz
